gtsfm/__init__.py
gtsfm/feature_extractor.py
gtsfm/multi_view_optimizer.py
gtsfm/scene_optimizer.py
gtsfm/two_view_estimator.py
gtsfm/assets/camera_details/sensor_database.csv
gtsfm/averaging/__init__.py
gtsfm/averaging/rotation/__init__.py
gtsfm/averaging/rotation/rig_shonan.py
gtsfm/averaging/rotation/rotation_averaging_base.py
gtsfm/averaging/rotation/shonan.py
gtsfm/averaging/translation/__init__.py
gtsfm/averaging/translation/averaging_1dsfm.py
gtsfm/averaging/translation/rig_1dsfm.py
gtsfm/averaging/translation/translation_averaging_base.py
gtsfm/bundle/__init__.py
gtsfm/bundle/bundle_adjustment.py
gtsfm/bundle/global_ba.py
gtsfm/bundle/rig_bundle_adjustment.py
gtsfm/bundle/two_view_ba.py
gtsfm/common/__init__.py
gtsfm/common/constraint.py
gtsfm/common/gtsfm_data.py
gtsfm/common/image.py
gtsfm/common/keypoints.py
gtsfm/common/pose_prior.py
gtsfm/common/sensor_width_database.py
gtsfm/common/sfm_track.py
gtsfm/common/two_view_estimation_report.py
gtsfm/common/types.py
gtsfm/common/view_frustum.py
gtsfm/configs/__init__.py
gtsfm/configs/correspondence/__init__.py
gtsfm/configs/verifier/__init__.py
gtsfm/data_association/__init__.py
gtsfm/data_association/data_assoc.py
gtsfm/data_association/dsf_tracks_estimator.py
gtsfm/data_association/point3d_initializer.py
gtsfm/data_association/tracks_estimator_base.py
gtsfm/evaluation/__init__.py
gtsfm/evaluation/compare_metrics.py
gtsfm/evaluation/merge_reports.py
gtsfm/evaluation/metrics.py
gtsfm/evaluation/metrics_report.py
gtsfm/evaluation/plot_metrics.py
gtsfm/evaluation/visualize_benchmark_comparison.py
gtsfm/frontend/__init__.py
gtsfm/frontend/inlier_support_processor.py
gtsfm/frontend/descriptor/__init__.py
gtsfm/frontend/descriptor/descriptor_base.py
gtsfm/frontend/descriptor/dummy_descriptor.py
gtsfm/frontend/descriptor/rootsift.py
gtsfm/frontend/descriptor/sift.py
gtsfm/frontend/detector/__init__.py
gtsfm/frontend/detector/detector_base.py
gtsfm/frontend/detector/detector_from_joint_detector_descriptor.py
gtsfm-0.2.0.dist-info/LICENSE
gtsfm-0.2.0.dist-info/METADATA
gtsfm-0.2.0.dist-info/WHEEL
gtsfm-0.2.0.dist-info/top_level.txt
gtsfm-0.2.0.dist-info/RECORD
