Metadata-Version: 2.1
Name: gtsfm
Version: 0.2.0
Home-page: 
Author: 
Author-email: 
License: BSD-3-Clause
Keywords: computer-vision
Classifier: Development Status :: 5 - Production/Stable
Classifier: Intended Audience :: Developers
Classifier: Operating System :: POSIX
Classifier: Operating System :: MacOS
Classifier: Programming Language :: Python :: 3
Classifier: Topic :: Scientific/Engineering :: Artificial Intelligence
Requires-Python: >= 3.6
License-File: LICENSE
